{
    "title": "Virtual ACC",
    "mask": "virtual_boot.css",
    "placeholder"  : "[modifier]",
    "builder": "michelangelo/kss_styleguide/brand-template/",
    "source": "./dist/css/",
    "destination": "docs/boot_virtual/",
    "//": "relative to source.",
    "homepage": "./markdown/virtual_boot_readme.md",
    "css": [
        "../icons/css/fontawesome.css",
        "../icons/css/solid.css",
        "../icons/css/regular.css",
        "../icons/css/brands.css",
        "../icons/css/light.css",
        "../icons/css/light.css",
        "../css/styleguide_override.css",
        "//fonts.googleapis.com/css?family=Roboto+Slab&display=swap",
        "//fonts.googleapis.com/css?family=Open+Sans:wght@400;500;700;900&display=swap",
        "//fonts.googleapis.com/css?family=Roboto&display=swap",
        "//fonts.googleapis.com/css2?family=Maven+Pro:wght@400;500;700;900&display=swap",
        "../css/color-code_social.css",
        "../css/color-code_credits.css",
        "../css/virtual_boot.css",
        "../css/virtual_uc.css"
    ],
    "js": ["https://cdn.jsdelivr.net/npm/@popperjs/core@2.9.2/dist/umd/popper.min.js","https://cdn.jsdelivr.net/npm/bootstrap@5.0.1/dist/js/bootstrap.bundle.min.js", "../js/toggleActive.js"],
    "custom": ["MarkupWrapperClasses","HideCodeBlock","Note","HideDefault","Format","SubComponents", "Data"],
    "site_nav": [
        { "title": "Arches", "id": "home_nav", "url": "../" },
        {
            "title": "Utility Classes",
            "id": "utility_classes",
            "url": "../utility_classes/"
        },
        {
            "title": "ACC",
            "id": "boot_acc",
            "url": "../boot_acc/"    
        },
        {
            "title": "CardioSmart",
            "id": "uc_cardiosmart",
            "url": "../boot_cardiosmart/"
        },
        {
            "title": "CVQuality",
            "id": "boot_cvquality",
            "url": "../boot_cvquality/"
        },
        {
            "title": "Virtual",
            "id": "boot_virtual",
            "url": "../boot_virtual/"
            ,"isActive": true       
        },
        {
            "title": "JACC",
            "id": "boot_journal",
            "url": "../boot_journal/"
        },
        {
            "title": "Color Codes",
            "id": "color_codes",
            "url": "../color_codes/"
        },
        {
            "title": "Icon Dictionary",
            "id": "icon_dictionary",
            "url": "https://acc-style.github.io/IconDictionary/"
            
        }
    ]
}